main.py
mcpproject-0.1.11.dist-info/METADATA
mcpproject-0.1.11.dist-info/WHEEL
mcpproject-0.1.11.dist-info/entry_points.txt
mcpproject-0.1.11.dist-info/top_level.txt
mcpproject-0.1.11.dist-info/RECORD
