Metadata-Version: 2.4
Name: mcpproject
Version: 0.1.11
Summary: Add your description here
Requires-Python: >=3.13
Requires-Dist: mcp>=1.7.1
